Reg_File.v
module Reg_File #(parameter ADDR_Width = 4, MEM_WIDTH = 16, MEM_DEPTH = 8)(
    input [MEM_WIDTH - 1 : 0]  WrData,
    input [ADDR_Width - 1 : 0] Address,
    input WrEn, RdEn,
    input CLK, RST,
    output reg [MEM_WIDTH - 1 : 0] RdData
);

// Memory Declration 
reg [MEM_WIDTH - 1 : 0] Memory [MEM_DEPTH - 1 : 0];
integer i;

always @(posedge CLK or negedge RST)
begin
    if(!RST)
        begin
            for(i = 0; i <= 7; i = i + 1)
                    Memory[i] <= 'b0;
            RdData <= 'b0;
        end

    // Write Operation
    else if (WrEn && !RdEn)
            Memory[Address] <= WrData;

    // Read Operation
    else if (RdEn && !WrEn)
            RdData <= Memory[Address];

    // Allowing Only 1 Operation otherwise Zero O/P
    else
            RdData <= 'b0;
end

endmodule

Reg_File_TB.v
module Reg_File_TB#(parameter ADDR_Width = 4, MEM_WIDTH = 16, MEM_DEPTH = 8)();
reg [MEM_WIDTH - 1 : 0] WrData_tb;
reg [ADDR_Width - 1 : 0] Address_tb;
reg WrEn_tb;
reg RdEn_tb;
reg CLK_tb;
reg RST_tb;
wire [MEM_WIDTH - 1 : 0] RdData_tb;

Reg_File #(.ADDR_Width(ADDR_Width), .MEM_WIDTH(MEM_WIDTH), .MEM_DEPTH(MEM_DEPTH)) M0 (
    .WrData(WrData_tb),
    .Address(Address_tb),
    .WrEn(WrEn_tb),
    .RdEn(RdEn_tb),
    .CLK(CLK_tb),
    .RST(RST_tb),
    .RdData(RdData_tb)
);

always #5 CLK_tb = ~CLK_tb;

initial begin
    $dumpfile("Reg_File.vcd");
    $dumpvars;
    // Starting time zero & RST
    CLK_tb = 1'b0;
    RST_tb = 1'b0;
    WrData_tb = 'b0;
    Address_tb = 'b0;
    WrEn_tb = 1'b0;
    RdEn_tb = 1'b0;

    #10
    RST_tb = 1'b1;

    // Write Operation
    #10
    WrData_tb = 'd13;
    Address_tb = 'd2;
    WrEn_tb = 1'b1;
   // $display("Test Case 1 Data_in = %d", WrData_tb);

    #10
    WrData_tb = 'd8;
    Address_tb = 'd6;
    WrEn_tb = 1'b1;
   // display("Test Case 2 Data_in = %d", WrData_tb);

    // Case 1 Validation 
    #10
    WrEn_tb = 1'b0;
    Address_tb = 'd2;
    RdEn_tb = 1'b1;
    #10
    if (RdData_tb == 'd13)
        $display("Test Case 1 passed");
    else
        $display("Test Case 1 Failed");

    // Case 2 Validation
    #10
    Address_tb = 'd6;
    RdEn_tb = 1'b1;
    #10
    if (RdData_tb == 'd8)
        $display("Test Case 2 passed");
    else
        $display("Test Case 2 Failed");

    // Case 3 -- 2 Enables in the same time
    #10
    RdEn_tb = 1'b1;
    WrEn_tb = 1'b1;
    Address_tb = 'd3;
    #10
    if(RdData_tb == 'b0)
        $display("Test Case 3 passed");
    else
        $display("Test Case 3 Failed");

    #10
    RST_tb = 1'b0;
    #20
    $stop;
end
endmodule

Reg_File.vcd
$date
	Mon Mar 04 13:43:19 2024
$end
$version
	ModelSim Version 10.1d
$end
$timescale
	1ps
$end
$scope module Reg_File_TB $end
$var parameter 32 ! ADDR_Width $end
$var parameter 32 " MEM_WIDTH $end
$var parameter 32 # MEM_DEPTH $end
$var reg 16 $ WrData_tb [15:0] $end
$var reg 4 % Address_tb [3:0] $end
$var reg 1 & WrEn_tb $end
$var reg 1 ' RdEn_tb $end
$var reg 1 ( CLK_tb $end
$var reg 1 ) RST_tb $end
$var wire 1 * RdData_tb [15] $end
$var wire 1 + RdData_tb [14] $end
$var wire 1 , RdData_tb [13] $end
$var wire 1 - RdData_tb [12] $end
$var wire 1 . RdData_tb [11] $end
$var wire 1 / RdData_tb [10] $end
$var wire 1 0 RdData_tb [9] $end
$var wire 1 1 RdData_tb [8] $end
$var wire 1 2 RdData_tb [7] $end
$var wire 1 3 RdData_tb [6] $end
$var wire 1 4 RdData_tb [5] $end
$var wire 1 5 RdData_tb [4] $end
$var wire 1 6 RdData_tb [3] $end
$var wire 1 7 RdData_tb [2] $end
$var wire 1 8 RdData_tb [1] $end
$var wire 1 9 RdData_tb [0] $end
$scope module M0 $end
$var parameter 32 : ADDR_Width $end
$var parameter 32 ; MEM_WIDTH $end
$var parameter 32 < MEM_DEPTH $end
$var wire 1 = WrData [15] $end
$var wire 1 > WrData [14] $end
$var wire 1 ? WrData [13] $end
$var wire 1 @ WrData [12] $end
$var wire 1 A WrData [11] $end
$var wire 1 B WrData [10] $end
$var wire 1 C WrData [9] $end
$var wire 1 D WrData [8] $end
$var wire 1 E WrData [7] $end
$var wire 1 F WrData [6] $end
$var wire 1 G WrData [5] $end
$var wire 1 H WrData [4] $end
$var wire 1 I WrData [3] $end
$var wire 1 J WrData [2] $end
$var wire 1 K WrData [1] $end
$var wire 1 L WrData [0] $end
$var wire 1 M Address [3] $end
$var wire 1 N Address [2] $end
$var wire 1 O Address [1] $end
$var wire 1 P Address [0] $end
$var wire 1 Q WrEn $end
$var wire 1 R RdEn $end
$var wire 1 S CLK $end
$var wire 1 T RST $end
$var reg 16 U RdData [15:0] $end
$var integer 32 V i $end
$upscope $end
$upscope $end
$enddefinitions $end
#0
$dumpvars
b0 $
b0 %
0&
0'
0(
0)
b0 U
b100 !
b10000 "
b1000 #
b100 :
b10000 ;
b1000 <
b1000 V
09
08
07
06
05
04
03
02
01
00
0/
0.
0-
0,
0+
0*
0T
0S
0R
0Q
0P
0O
0N
0M
0L
0K
0J
0I
0H
0G
0F
0E
0D
0C
0B
0A
0@
0?
0>
0=
$end
#5
1(
1S
b0 V
b1 V
b10 V
b11 V
b100 V
b101 V
b110 V
b111 V
b1000 V
#10
1)
0(
1T
0S
#15
1(
1S
#20
b1101 $
b10 %
1&
0(
1O
1L
1J
1I
1Q
0S
#25
1(
1S
#30
b1000 $
b110 %
0(
1N
0L
0J
0S
#35
1(
1S
#40
0&
b10 %
1'
0(
0Q
0N
1R
0S
#45
1(
1S
b1101 U
19
17
16
#50
0(
0S
#55
1(
1S
#60
b110 %
0(
1N
0S
#65
1(
1S
b1000 U
09
07
#70
0(
0S
#75
1(
1S
#80
1&
b11 %
0(
1Q
1P
0N
0S
#85
1(
1S
b0 U
06
#90
0(
0S
#95
1(
1S
#100
0)
0(
0T
0S
b0 V
b1 V
b10 V
b11 V
b100 V
b101 V
b110 V
b111 V
b1000 V
#105
1(
1S
b0 V
b1 V
b10 V
b11 V
b100 V
b101 V
b110 V
b111 V
b1000 V
#110
0(
0S
#115
1(
1S
b0 V
b1 V
b10 V
b11 V
b100 V
b101 V
b110 V
b111 V
b1000 V
